texttoppt/__init__.py
texttoppt/chatParser.py
texttoppt/orchestrator.py
texttoppt/slideGenerator.py
TextToPPT-0.1.9.dist-info/LICENSE.txt
TextToPPT-0.1.9.dist-info/METADATA
TextToPPT-0.1.9.dist-info/WHEEL
TextToPPT-0.1.9.dist-info/top_level.txt
TextToPPT-0.1.9.dist-info/RECORD
