Metadata-Version: 2.1
Name: TextToPPT
Version: 0.1.9
Summary: Converting Text To PPT
Home-page: https://github.com/jatinshrivastava/TextToPPT-Library
Author: Suryansh Pandey
Author-email: suryanshpan29@gmail.com
License: UNKNOWN
Platform: UNKNOWN
Classifier: Programming Language :: Python :: 3
Classifier: License :: OSI Approved :: MIT License
Classifier: Operating System :: OS Independent
